rasa_paddlenlp/__init__.py
rasa_paddlenlp/nlu/__init__.py
rasa_paddlenlp/nlu/paddlenlp_featurizer.py
rasa_paddlenlp/nlu/paddlenlp_registry.py
rasa_paddlenlp/nlu/paddlenlp_tokenizer.py
rasa_paddlenlp-0.3.1.dist-info/LICENSE
rasa_paddlenlp-0.3.1.dist-info/METADATA
rasa_paddlenlp-0.3.1.dist-info/WHEEL
rasa_paddlenlp-0.3.1.dist-info/top_level.txt
rasa_paddlenlp-0.3.1.dist-info/RECORD
