Metadata-Version: 2.1
Name: rasa-paddlenlp
Version: 0.3.1
Summary: Rasa NLU Components with PaddleNLP
Home-page: https://github.com/botisan-ai/rasa-paddlenlp
Author: Simon Liang
Author-email: simon@x-tech.io
License: MIT license
Keywords: rasa_paddlenlp
Platform: UNKNOWN
Classifier: Development Status :: 2 - Pre-Alpha
Classifier: Intended Audience :: Developers
Classifier: License :: OSI Approved :: MIT License
Classifier: Natural Language :: English
Classifier: Programming Language :: Python :: 3
Classifier: Programming Language :: Python :: 3.7
Classifier: Programming Language :: Python :: 3.8
Requires-Python: >=3.7
License-File: LICENSE
Requires-Dist: rasa (>=3)
Requires-Dist: paddlepaddle (==2.2.2)
Requires-Dist: paddlenlp (==2.2.4)
